[
  {
    "id": 1,
    "name": "Make-up",
    "position": "Event Coordinator",
    "img": "https://i.ibb.co/wy6gpQy/amy-shamblen-xw-M61-TPMl-Yk-unsplash.jpg"
  },
  {
    "id": 2,
    "name": "Lipsticks",
    "position": "Marketing Manager",
    "img": "https://i.ibb.co/kqzxt85/pexels-steven-john-pascua-4416763.jpg"
  },
  {
    "id": 3,
    "name": "perfume",
    "position": "Logistics Coordinator",
    "img": "https://i.ibb.co/41nwFh6/yixian-zhao-q7i-ZCOXGOWY-unsplash.jpg"
  },
  {
    "id": 4,
    "name": "Shampoo",
    "position": "Logistics Coordinator",
    "img": "https://i.ibb.co/7jgvJJ4/pexels-behrouz-alimardani-10644997.jpg"
  }
]